rediswq/__init__.py
rediswq-0.1.dist-info/LICENSE.txt
rediswq-0.1.dist-info/METADATA
rediswq-0.1.dist-info/WHEEL
rediswq-0.1.dist-info/top_level.txt
rediswq-0.1.dist-info/RECORD
