Metadata-Version: 2.1
Name: rediswq
Version: 0.1
Summary: A Redis-based work queue
Home-page: https://github.com/vringar/rediswq
Author: vringar
Author-email: h_dieter@mail.ru
License: UNKNOWN
Project-URL: Bug Reports, https://github.com/vringar/rediswq/issues
Project-URL: Source, https://github.com/vringar/rediswq/
Keywords: redis,distributed
Platform: UNKNOWN
Classifier: Development Status :: 3 - Alpha
Classifier: Intended Audience :: Developers
Classifier: Environment :: Console
Classifier: License :: OSI Approved :: MIT License
Classifier: Programming Language :: Python :: 3
Classifier: Programming Language :: Python :: 3.6
Classifier: Programming Language :: Python :: 3.7
Classifier: Programming Language :: Python :: 3.8
Classifier: Programming Language :: Python :: 3.9
Classifier: Programming Language :: Python :: 3 :: Only
Requires-Python: >=3.6, <4
License-File: LICENSE.txt
Requires-Dist: redis
Provides-Extra: dev
Requires-Dist: mypy ; extra == 'dev'
Requires-Dist: black ; extra == 'dev'
Requires-Dist: flake8 ; extra == 'dev'
Requires-Dist: check-manifest ; extra == 'dev'
Provides-Extra: test
Requires-Dist: tox ; extra == 'test'
Requires-Dist: coverage ; extra == 'test'
